coininfo_arezou/__init__.py
coininfo_arezou/info.py
coininfo_arezou-1.1.4.dist-info/METADATA
coininfo_arezou-1.1.4.dist-info/WHEEL
coininfo_arezou-1.1.4.dist-info/top_level.txt
coininfo_arezou-1.1.4.dist-info/RECORD
