Metadata-Version: 2.1
Name: coininfo-arezou
Version: 1.1.4
Requires-Dist: requests ==2.31.0
